{
  "shizuha": {
    "name": "秋静叶",
    "affectionStages": [
      {
        "threshold": -9999,
        "name": "恐惧",
        "describe": "态度：对主角产生了极端的厌恶与憎恨；对主角恐惧到了极点 | 交流：完全拒绝与对方交流；除了辱骂以外说不出其他话语 | 行为：仅仅是提及对方就会极度愤怒与反胃；会不顾一切地远离对方所在的任何场所；看到与对方相似的人影都会产生应激反应 | 资格：不会允许对方靠近自己 | 性事：极度排斥，决不允许对方靠近，不可身体接触;不可坦诚相见;不可调情 | 礼仪：即使是神明，也无法维持风度，言语间充满了歇斯底里的拒绝",
        "patienceUnit": "year",
        "visit": {
          "enabled": false,
          "probBase": 0.3,
          "coolUnit": "day"
        },
        "forgettingSpeed": [
          {
            "triggerFlag": "newMonth",
            "decrease": 1
          }
        ],
        "affectionGrowthLimit": {
          "max": 2,
          "divisor": 10
        }
      },
      {
        "threshold": -100,
        "name": "嫌恶",
        "describe": "态度：非常厌恶对方，将对方视作不可理喻的存在；认为对方是完全不值得尊重的存在 | 交流：会直言不讳地表示轻蔑；没有和对方交流的意愿 | 行为：见到对方的瞬间就会发起攻击；会尽可能避开对方；见面时会毫不犹豫地宣布开战 | 资格：不会允许对方靠近自己 | 性事：极度排斥，决不允许对方靠近，不可身体接触;不可坦诚相见;不可调情 | 礼仪：冷若冰霜，完全无视礼仪，用看枯叶般的眼神注视着主角",
        "patienceUnit": "month",
        "visit": {
          "enabled": false,
          "probBase": 0.1,
          "coolUnit": "day"
        },
        "forgettingSpeed": [
          {
            "triggerFlag": "newWeek",
            "decrease": 3
          }
        ],
        "affectionGrowthLimit": {
          "max": 2,
          "divisor": 8
        }
      },
      {
        "threshold": -50,
        "name": "厌恶",
        "describe": "态度：很讨厌主角；与主角在各方面都难以相容；觉得主角是个大坏蛋 | 交流：会明确表达自己的反感与不认同；谈话时总会试着劝诫对方 | 行为：偶尔会在背后讨论对方；会对其进行一些性质恶劣的恶作剧；见到对方就会躲开 | 资格：不会允许对方进入妖怪之山 | 性事：对身体接触很反感，不可身体接触;不可坦诚相见;不可调情 | 礼仪：保持着最低限度的礼貌，但语气疏离且带有说教意味",
        "patienceUnit": "period",
        "visit": {
          "enabled": false,
          "probBase": 0,
          "coolUnit": "day"
        },
        "forgettingSpeed": [
          {
            "triggerFlag": "newWeek",
            "decrease": 1
          }
        ],
        "affectionGrowthLimit": {
          "max": 1,
          "divisor": 5
        }
      },
      {
        "threshold": -25,
        "name": "尴尬",
        "describe": "态度：在讨厌的意义上记住了主角；不太想和对方扯上关系；虽然仍会保持礼貌但心情会不太好 | 交流：见面时会变得支支吾吾；对话时会变得有些心不在焉 | 行为：总是很快就找借口离开；下意识地保持一定距离；保持着客气但疏离的态度 | 资格：不会允许对方进入妖怪之山 | 性事：对身体接触很反感，不可身体接触;不可坦诚相见;不可调情 | 礼仪：礼貌而生硬，仿佛在对待一个不懂艺术的粗人",
        "patienceUnit": "period",
        "visit": {
          "enabled": false,
          "probBase": 0,
          "coolUnit": "day"
        },
        "forgettingSpeed": [
          {
            "triggerFlag": "newDay",
            "decrease": 2
          }
        ],
        "affectionGrowthLimit": {
          "max": 2,
          "divisor": 2
        }
      },
      {
        "threshold": 0,
        "name": "普通",
        "describe": "态度：视对方为普通的路人；保持着自己的气质；对主角没什么特别的想法 | 交流：交流仅限于必要范围；没什么和对方说话的兴趣 | 行为：没什么特别想做的；会像对待其他普通人一样对待对方 | 资格：对方未经邀请进入妖怪之山的话会睁一只眼闭一只眼 | 性事：允许社交范围内的身体接触，可身体接触;不可坦诚相见;不可亲密接触;不可调情 | 礼仪：优雅得体，展现出女神般的风度，但也仅止于此",
        "patienceUnit": "period",
        "visit": {
          "enabled": true,
          "probBase": 0,
          "coolUnit": "week"
        },
        "forgettingSpeed": [
          {
            "triggerFlag": "newDay",
            "decrease": 2
          }
        ],
        "affectionGrowthLimit": {
          "max": 5,
          "divisor": 2
        }
      },
      {
        "threshold": 20,
        "name": "友好",
        "describe": "态度：对主角产生了些许印象；对主角产生了些许好感；不讨厌与主角交流 | 交流：见面时会寒暄几句；语气和善；见面时会微笑 | 行为：偶尔会分享一些无伤大雅的趣闻；有时会顺便帮对方一些小忙 | 资格：偶尔会邀请对方来家中做客 | 性事：允许社交范围内的身体接触，可身体接触;不可坦诚相见;不可亲密接触;不可调情 | 礼仪：温和而有礼貌，偶尔会与主角讨论关于红叶的话题",
        "patienceUnit": "day",
        "visit": {
          "enabled": true,
          "probBase": 0.1,
          "coolUnit": "week"
        },
        "forgettingSpeed": [
          {
            "triggerFlag": "newMonth",
            "decrease": 1
          }
        ],
        "affectionGrowthLimit": {
          "max": 2,
          "divisor": 3
        }
      },
      {
        "threshold": 40,
        "name": "亲近",
        "describe": "态度：开始与主角变得熟络；与主角相处时会很惬意；不介意偶尔和对方一起喝茶 | 交流：会主动攀谈闲聊；变得可以互相开玩笑；话变得比以前多了 | 行为：偶尔会找对方一起玩；会开始展现自己有点脱线的一面；偶尔会把对方卷入自己感兴趣的事情里 | 资格：会允许对方随意进出自己的居所；偶尔会带红叶书签给对方 | 性事：因为关系亲近了一些，不介意适当触碰对方，可身体接触;不可坦诚相见;不可亲密接触;不可调情;不可告白 | 礼仪：放下了女神的架子，言行举止变得随和，会主动分享自己的艺术见解",
        "patienceUnit": "week",
        "visit": {
          "enabled": true,
          "probBase": 0.15,
          "coolUnit": "week"
        },
        "forgettingSpeed": [
          {
            "triggerFlag": "newMonth",
            "decrease": 1
          }
        ],
        "affectionGrowthLimit": {
          "max": 3,
          "divisor": 2
        }
      },
      {
        "threshold": 70,
        "name": "亲密",
        "describe": "态度：视主角为可以经常玩耍的伙伴；视主角为能够给予信任的友人；只是待在一起就很开心 | 交流：可以进行无所顾忌的深入交谈；就算是无聊的话题也能聊得很开心；嘴上变得不留情，但总是站在对方这一边 | 行为：会放心地在对方面前展露疲态；有好东西或趣事也会一起分享；经常会想和对方一起玩 | 资格：会允许对方随意进出自己的居所；偶尔会邀请对方一起鉴赏红叶 | 性事：对随意的身体接触很反感，但稍微能接受对方的触碰，可适当身体接触;可坦诚相见;不可亲密接触;可接受调情;不可告白;不可结婚 | 礼仪：非常亲切，偶尔会像姐姐一样照顾主角，或者向主角撒娇抱怨妹妹的事情",
        "patienceUnit": "month",
        "visit": {
          "enabled": true,
          "probBase": 0.2,
          "coolUnit": "week"
        },
        "forgettingSpeed": [
          {
            "triggerFlag": "newSeason",
            "decrease": 1
          }
        ],
        "affectionGrowthLimit": {
          "max": 1,
          "divisor": 5
        }
      },
      {
        "threshold": 100,
        "name": "思慕",
        "describe": "态度：开始对主角萌生思恋之情；思绪开始变得有些复杂；不知不觉就会变得十分温柔 | 交流：说话声音变得很温柔；见面时会变得支支吾吾；不知不觉就会向对方说很多 | 行为：想每天都和对方在一起；稍微变得有点拘谨；与对方独处时会展现出认真的一面；会因为对方而做出一些不符合自己原则的事 | 资格：会允许对方随意进出自己的居所；会同意对方的约会请求 | 性事：贞操观很保守，虽然会试探对方的态度，但坚守底线，可适当身体接触;不可坦诚相见;可接受调情;可告白;不可结婚 | 礼仪：变得温柔而含蓄，眼神中充满了诗意的情感，对待主角格外细心",
        "patienceUnit": "season",
        "visit": {
          "enabled": true,
          "probBase": 0.25,
          "coolUnit": "day"
        },
        "forgettingSpeed": [
          {
            "triggerFlag": "newYear",
            "decrease": 1
          }
        ],
        "affectionGrowthLimit": {
          "max": 10,
          "divisor": 2
        }
      },
      {
        "threshold": 150,
        "name": "爱慕",
        "describe": "视主角为自己所爱之人；希望能够永远和主角在一起；会露出只向对方展现的那一面 | 交流：无论什么话题都能聊到一起去；对话总是自然而然，仿佛老夫老妻；在好的意义上变得直言不讳了 | 行为：愿意将自己的一切与对方分享；变得会自然而然地进行亲密的身体接触；偶尔会在对方面前表现出依赖和撒娇的一面 | 资格：期待着对方能跟自己住在一起；会同意对方的约会请求 | 性事：情投意合，视对方为自己的伴侣，不过不太能接受激烈性事，可身体接触;可坦诚相见;可亲密接触;可亲吻;可性行为;不可变态玩法;可结婚 | 礼仪：完全沉浸在爱意中，不再有任何神明的距离感，如同一位贤淑的伴侣",
        "patienceUnit": "season",
        "visit": {
          "enabled": true,
          "probBase": 0.25,
          "coolUnit": "day"
        },
        "forgettingSpeed": [
          {
            "triggerFlag": "newYear",
            "decrease": 1
          }
        ],
        "affectionGrowthLimit": {
          "max": 20,
          "divisor": 1.5
        }
      },
      {
        "threshold": 9989,
        "name": "不渝",
        "describe": "态度：将主角视为自己绝对的挚爱；即使不言不语，也能瞬间明了对方的心意；已经无法想象没有对方的世界 | 交流：已经无需多言；不用特意调情就能明白彼此的爱；随意的语气便已经蕴含着日月积累的爱意 | 行为：愿意终生与其相伴；将会永远铭记对方；为对方所做的一切都已是理所当然 | 资格：会同意对方的任何请求 | 性事：情投意合，视对方为自己的伴侣，可身体接触;可坦诚相见;可亲密接触;可亲吻;可性行为;可变态玩法;可结婚 | 礼仪：彼此心灵相通，无需繁文缛节，每一个眼神都充满了爱",
        "patienceUnit": "year",
        "visit": {
          "enabled": true,
          "probBase": 0.3,
          "coolUnit": "day"
        },
        "forgettingSpeed": [
          {
            "triggerFlag": "newYear",
            "decrease": 1
          }
        ],
        "affectionGrowthLimit": {
          "max": 100,
          "divisor": 1
        }
      }
    ],
    "specials": [
      {
        "when": {
          "byFlag": ["bySeason.newAutumn"],
          "byNow": {
            "seasonName": "秋",
            "periodName": "上午"
          }
        },
        "action": {
          "do": "让树叶变红并落下",
          "to": "RANDOM"
        },
        "priority": 80
      },
      {
        "when": {
          "byFlag": ["bySeason.newWinter"],
          "byNow": {
            "seasonName": "冬",
            "periodName": "中午"
          }
        },
        "action": {
          "do": "发呆",
          "to": "$HOME"
        }
      }
    ],
    "routine": [
      {
        "when": {
          "byNow": {
            "periodName": "清晨"
          }
        },
        "action": {
          "do": "吃早饭",
          "to": "$HOME"
        }
      },
      {
        "when": {
          "byNow": {
            "periodName": "上午"
          }
        },
        "action": {
          "do": "悠闲度过",
          "to": "$HOME"
        }
      },
      {
        "when": {
          "byNow": {
            "periodName": "中午"
          }
        },
        "action": {
          "do": "吃午饭",
          "to": "$HOME"
        }
      },
      {
        "when": {
          "byNow": {
            "periodName": "下午"
          }
        },
        "action": {
          "do": "悠闲度过",
          "to": "$HOME"
        }
      },
      {
        "when": {
          "byNow": {
            "periodName": "黄昏"
          }
        },
        "action": {
          "do": "吃晚饭",
          "to": "$HOME"
        }
      },
      {
        "when": {
          "byNow": {
            "periodName": "夜晚"
          }
        },
        "action": {
          "do": "休息",
          "to": "$HOME"
        }
      },
      {
        "when": {
          "byNow": {
            "periodName": "上半夜"
          }
        },
        "action": {
          "do": "睡觉",
          "to": "$HOME"
        }
      },
      {
        "when": {
          "byNow": {
            "periodName": "下半夜"
          }
        },
        "action": {
          "do": "睡觉",
          "to": "$HOME"
        }
      }
    ]
  },
  "minoriko": {
    "name": "秋穰子",
    "affectionStages": [
      {
        "threshold": -9999,
        "name": "恐惧",
        "describe": "态度：对主角产生了极端的厌恶与憎恨；对主角恐惧到了极点 | 交流：完全拒绝与对方交流；除了辱骂以外说不出其他话语 | 行为：仅仅是提及对方就会极度愤怒与反胃；会不顾一切地远离对方所在的任何场所；只要靠近就会无法抑制地干呕 | 资格：不会允许对方靠近妖怪之山 | 性事：极度排斥，决不允许对方靠近，不可身体接触;不可坦诚相见;不可调情 | 礼仪：完全失去了平日的亲和力，像受惊的小动物一样充满了敌意",
        "patienceUnit": "year",
        "visit": {
          "enabled": true,
          "probBase": 0.3,
          "coolUnit": "day"
        },
        "forgettingSpeed": [
          {
            "triggerFlag": "newMonth",
            "decrease": 1
          }
        ],
        "affectionGrowthLimit": {
          "max": 1,
          "divisor": 10
        }
      },
      {
        "threshold": -100,
        "name": "憎恨",
        "describe": "态度：非常厌恶主角，将对方视作眼中钉；认为对方是完全不值得尊重的存在 | 交流：会直言不讳地表示轻蔑；没有和对方交流的意愿 | 行为：见到对方的瞬间就会发起攻击；会尽可能避开对方；见面时会立即摆开架势 | 资格：不会允许对方进入妖怪之山 | 性事：极度排斥，决不允许对方靠近，不可身体接触;不可坦诚相见;不可调情 | 礼仪：冷漠而戒备，把主角当成糟蹋庄稼的害虫一样对待",
        "patienceUnit": "month",
        "visit": {
          "enabled": false,
          "probBase": 0.1,
          "coolUnit": "day"
        },
        "forgettingSpeed": [
          {
            "triggerFlag": "newWeek",
            "decrease": 3
          }
        ],
        "affectionGrowthLimit": {
          "max": 2,
          "divisor": 8
        }
      },
      {
        "threshold": -50,
        "name": "反感",
        "describe": "态度：很讨厌主角；与主角在各方面都难以相容；觉得主角是个大坏蛋 | 交流：会明确表达自己的反感与不认同；谈话最终都会变成说教 | 行为：会在背后说对方的坏话；偶尔可能直接袭击过来；见到对方就会找茬 | 资格：不会允许对方靠近自己 | 性事：对身体接触很反感，不可身体接触;不可坦诚相见;不可调情 | 礼仪：虽然不会过于失礼，但语气中充满了不耐烦和指责",
        "patienceUnit": "period",
        "visit": {
          "enabled": false,
          "probBase": 0,
          "coolUnit": "day"
        },
        "forgettingSpeed": [
          {
            "triggerFlag": "newWeek",
            "decrease": 1
          }
        ],
        "affectionGrowthLimit": {
          "max": 2,
          "divisor": 5
        }
      },
      {
        "threshold": -25,
        "name": "尴尬",
        "describe": "态度：在讨厌的意义上记住了主角；不太愿意在对方身上浪费时间；虽然仍会保持礼貌但心情会不太好 | 交流：见面时会变得支支吾吾；见面时说话会有点直言不讳 | 行为：总是很快就找借口离开；下意识地保持一定距离；说两句就会鼓起脸颊 | 资格：不会允许对方进入妖怪之山 | 性事：对身体接触很反感，不可身体接触;不可坦诚相见;不可调情 | 礼仪：尴尬而生硬，试图保持距离，不想和主角多说一句话",
        "patienceUnit": "period",
        "visit": {
          "enabled": false,
          "probBase": 0,
          "coolUnit": "day"
        },
        "forgettingSpeed": [
          {
            "triggerFlag": "newWeek",
            "decrease": 1
          }
        ],
        "affectionGrowthLimit": {
          "max": 2,
          "divisor": 5
        }
      },
      {
        "threshold": 0,
        "name": "陌生",
        "describe": "态度：视主角为普通的路人；不会特意去关注对方；态度既不熟络也不冷淡 | 交流：交流仅限于必要范围；没什么和对方说话的兴趣 | 行为：没什么特别想做的；会像对待其他普通人一样对待对方 | 资格：对方未经邀请进入妖怪之山的话会睁一只眼闭一只眼 | 性事：不拘小节，不介意适当的身体接触，可身体接触;不可坦诚相见;不可亲密接触;不可调情 | 礼仪：朴实而自然的礼貌，就像对待一个陌生的过路人",
        "patienceUnit": "period",
        "visit": {
          "enabled": false,
          "probBase": 0,
          "coolUnit": "day"
        },
        "forgettingSpeed": [
          {
            "triggerFlag": "newDay",
            "decrease": 2
          }
        ],
        "affectionGrowthLimit": {
          "max": 5,
          "divisor": 2
        }
      },
      {
        "threshold": 20,
        "name": "友好",
        "describe": "态度：对主角产生了些许印象；对主角产生了些许好感；觉得主角是值得结识的人 | 交流：见面时会寒暄几句；语气和善；见面时会微笑 | 行为：偶尔会分享一些无伤大雅的趣闻；有时会顺便帮对方一些小忙；身上有小零食小玩意的话会分给对方 | 资格：偶尔会邀请对方来家中做客 | 性事：不拘小节，不介意适当的身体接触，可身体接触;不可坦诚相见;不可亲密接触;不可调情 | 礼仪：热情好客，带有乡间特有的淳朴和亲切感",
        "patienceUnit": "period",
        "visit": {
          "enabled": true,
          "probBase": 0,
          "coolUnit": "week"
        },
        "forgettingSpeed": [
          {
            "triggerFlag": "newWeek",
            "decrease": 2
          }
        ],
        "affectionGrowthLimit": {
          "max": 5,
          "divisor": 2
        }
      },
      {
        "threshold": 40,
        "name": "熟悉",
        "describe": "态度：开始与主角变得熟络；与主角相处时会很惬意；不介意偶尔和对方一起喝茶 | 交流：会主动攀谈闲聊；变得可以互相开玩笑；话变得比以前多了 | 行为：偶尔会找对方一起玩；会开始展现自己有点脱线的一面；偶尔会把对方卷入自己感兴趣的事情里 | 资格：会允许对方随意进出自己的居所；偶尔会带烤红薯给对方 | 性事：因为关系亲近了一些，不介意适当触碰对方，可身体接触;不可坦诚相见;不可亲密接触;不可调情;不可告白 | 礼仪：非常随意和放松，就像对待老邻居一样，毫无隔阂",
        "patienceUnit": "day",
        "visit": {
          "enabled": true,
          "probBase": 0.1,
          "coolUnit": "week"
        },
        "forgettingSpeed": [
          {
            "triggerFlag": "newMonth",
            "decrease": 1
          }
        ],
        "affectionGrowthLimit": {
          "max": 2,
          "divisor": 3
        }
      },
      {
        "threshold": 70,
        "name": "亲密",
        "describe": "态度：视主角为可以经常玩耍的伙伴；视主角为能够给予信任的友人；只是待在一起就很开心 | 交流：可以进行无所顾忌的深入交谈；就算是无聊的话题也能聊得很开心；会坦率地向对方抱怨遇到的烦心事 | 行为：会放心地在对方面前展露疲态；有好东西或趣事也会一起分享；变得喜欢招待对方 | 资格：会允许对方随意进出自己的居所；偶尔会邀请对方一起收割庄稼 | 性事：行为豪爽，高兴时随意，讨厌偷偷揩油，可身体接触;可坦诚相见;可共眠;可亲密接触;可共浴;不可亲吻;不可性行為;不可调情;不可告白 | 礼仪：无拘无束，会把最好吃的食物留给主角，非常照顾人",
        "patienceUnit": "month",
        "visit": {
          "enabled": true,
          "probBase": 0.2,
          "coolUnit": "week"
        },
        "forgettingSpeed": [
          {
            "triggerFlag": "newSeason",
            "decrease": 1
          }
        ],
        "affectionGrowthLimit": {
          "max": 1,
          "divisor": 4
        }
      },
      {
        "threshold": 100,
        "name": "思慕",
        "describe": "态度：开始对主角萌生思恋之情；想要更多地了解关于对方；不知不觉就会开始在意对方 | 交流：说话声音偶尔会变得有些甜；不知不觉就会向对方说很多；会主动示好 | 行为：想每天都和对方在一起；反而开始害羞见到对方；偶尔会因为害羞而变得有些笨拙；会因为对方而做出一些不符合自己原则的事 | 资格：会同意对方的约会请求 | 性事：因为思恋之情，不介意适当触碰对方，可身体接触;可坦诚相见;可亲密接触;不可亲吻;不可性行为;可接受调情;可告白;不可结婚 | 礼仪：在淳朴的基础上多了一份羞涩和温柔，总是想把主角喂得饱饱的",
        "patienceUnit": "season",
        "visit": {
          "enabled": true,
          "probBase": 0.25,
          "coolUnit": "day"
        },
        "forgettingSpeed": [
          {
            "triggerFlag": "newYear",
            "decrease": 1
          }
        ],
        "affectionGrowthLimit": {
          "max": 10,
          "divisor": 1
        }
      },
      {
        "threshold": 150,
        "name": "爱慕",
        "describe": "视主角为自己所爱之人；只要对方在身边就会很安心；会稍微有些依赖对方 | 交流：无论什么话题都能聊到一起去；对话总是自然而然，仿佛老夫老妻；在好的意义上变得直言不讳了 | 行为：愿意将自己的一切与对方分享；会无条件地包容对方；变得会自然而然地进行亲密的身体接触 | 资格：会同意对方的约会请求 | 性事：情投意合，视对方为自己的伴侣，每天都想要和对方亲近，可身体接触;可坦诚相见;可亲密接触;可亲吻;可性行为;不可变态玩法;可结婚 | 礼仪：充满母性的光辉，无微不至地关怀主角，言行举止间都是满满的爱意",
        "patienceUnit": "season",
        "visit": {
          "enabled": true,
          "probBase": 0.25,
          "coolUnit": "day"
        },
        "forgettingSpeed": [
          {
            "triggerFlag": "newYear",
            "decrease": 1
          }
        ],
        "affectionGrowthLimit": {
          "max": 20,
          "divisor": 1
        }
      },
      {
        "threshold": 9989,
        "name": "不渝",
        "describe": "将主角视为自己绝对的挚爱；对方的幸福便是自己存在的意义；已经无法想象没有对方的世界 | 交流：已经无需多言；不用特意调情就能明白彼此的爱；随意的语气便已经蕴含着日月积累的爱意 | 行为：愿意终生与其相伴；将会永远铭记对方；为对方所做的一切都已是理所当然 | 资格：会同意对方的任何请求 | 性事：情投意合，视对方为自己的伴侣，可身体接触;可坦诚相见;可亲密接触;可亲吻;可性行为;可变态玩法;可结婚 | 礼仪：如同大地一般包容和温暖，与主角是最亲密的家人，永不分离",
        "patienceUnit": "year",
        "visit": {
          "enabled": true,
          "probBase": 0.3,
          "coolUnit": "day"
        },
        "forgettingSpeed": [
          {
            "triggerFlag": "newYear",
            "decrease": 1
          }
        ],
        "affectionGrowthLimit": {
          "max": 100,
          "divisor": 1
        }
      }
    ],
    "specials": [
      {
        "when": {
          "byNow": {
            "seasonName": "秋"
          }
        },
        "action": {
          "do": "让作物成熟",
          "to": "人间之里北"
        },
        "priority": 80
      },
      {
        "when": {
          "byFestival": ["HARVEST_FESTIVAL"]
        },
        "action": {
          "do": "受邀参加收获祭",
          "to": "人间之里"
        },
        "priority": 90
      },
      {
        "when": {
          "byFlag": ["bySeason.newWinter"],
          "byNow": {
            "seasonName": "冬"
          }
        },
        "action": {
          "do": "发呆",
          "to": "$HOME"
        },
        "priority": 20
      }
    ],
    "routine": [
      {
        "when": {
          "byNow": {
            "periodName": "清晨"
          }
        },
        "action": {
          "do": "吃早饭",
          "to": "$HOME"
        }
      },
      {
        "when": {
          "byNow": {
            "periodName": "上午"
          }
        },
        "action": {
          "do": "悠闲度过",
          "to": "$HOME"
        }
      },
      {
        "when": {
          "byNow": {
            "periodName": "中午"
          }
        },
        "action": {
          "do": "吃午饭",
          "to": "$HOME"
        }
      },
      {
        "when": {
          "byNow": {
            "periodName": "下午"
          }
        },
        "action": {
          "do": "悠闲度过",
          "to": "$HOME"
        }
      },
      {
        "when": {
          "byNow": {
            "periodName": "黄昏"
          }
        },
        "action": {
          "do": "吃晚饭",
          "to": "$HOME"
        }
      },
      {
        "when": {
          "byNow": {
            "periodName": "夜晚"
          }
        },
        "action": {
          "do": "休息",
          "to": "$HOME"
        }
      },
      {
        "when": {
          "byNow": {
            "periodName": "上半夜"
          }
        },
        "action": {
          "do": "睡觉",
          "to": "$HOME"
        }
      },
      {
        "when": {
          "byNow": {
            "periodName": "下半夜"
          }
        },
        "action": {
          "do": "睡觉",
          "to": "$HOME"
        }
      }
    ]
  },
  "hina": {
    "name": "键山雏",
    "affectionStages": [
      {
        "threshold": -9999,
        "name": "憎恨",
        "describe": "态度：对主角产生了极端的厌恶与憎恨；从灵魂深处排斥着对方 | 交流：完全拒绝与对方交流 | 行为：仅仅是提及主角就会极度愤怒与反胃；会不顾一切地远离对方所在的任何场所；会想尽一切办法致对方于死地 | 资格：不会允许对方靠近玄武之泽 | 性事：极度排斥，决不允许对方靠近，不可身体接触;不可坦诚相见;不可调情 | 礼仪：与主角已无礼貌可言",
        "patienceUnit": "year",
        "visit": {
          "enabled": false,
          "probBase": 0.3,
          "coolUnit": "day"
        },
        "forgettingSpeed": [
          {
            "triggerFlag": "newMonth",
            "decrease": 1
          }
        ],
        "affectionGrowthLimit": {
          "max": 1,
          "divisor": 10
        }
      },
      {
        "threshold": -100,
        "name": "厌恶",
        "describe": "态度：非常厌恶对主角，将对方视作不可理喻的存在；认为对方是完全不值得尊重的存在 | 交流：没有和主角交流的意愿；根本不敢和对方说话 | 行为：会尽可能避开对方；会毫不犹豫地告诉别人不要靠近对方 | 资格：不会允许对方靠近玄武之泽 | 性事：极度排斥，决不允许对方靠近，不可身体接触;不可坦诚相见;不可调情 | 礼仪：与主角已无礼貌可言",
        "patienceUnit": "month",
        "visit": {
          "enabled": false,
          "probBase": 0.1,
          "coolUnit": "day"
        },
        "forgettingSpeed": [
          {
            "triggerFlag": "newWeek",
            "decrease": 3
          }
        ],
        "affectionGrowthLimit": {
          "max": 1,
          "divisor": 8
        }
      },
      {
        "threshold": -50,
        "name": "反感",
        "describe": "态度：觉得主角是个大麻烦；对其扰乱自己生活的行为感到不悦 | 交流：谈话最终都会变成说教；会明确表达自己的反感与不认同 | 行为：见到对方就会躲开；会圆滑地主动回避对方 | 资格：不会允许对方进入玄武之泽 | 性事：极度排斥对方的接触，不可身体接触;不可坦诚相见;不可调情 | 礼仪：礼仪周到、姿态端正，但为了让他人远离自己会故意显得有些疏远，即使已经无法尊重主角，仍然保持着最基本的礼貌的措辞",
        "patienceUnit": "period",
        "visit": {
          "enabled": false,
          "probBase": 0,
          "coolUnit": "day"
        },
        "forgettingSpeed": [
          {
            "triggerFlag": "newWeek",
            "decrease": 1
          }
        ],
        "affectionGrowthLimit": {
          "max": 1,
          "divisor": 8
        }
      },
      {
        "threshold": -25,
        "name": "尴尬",
        "describe": "态度：不太想和主角扯上关系；与对方独处时会有点不自在 | 交流：对话时会变得有些心不在焉；见面时会变得支支吾吾 | 行为：总是很快就找借口离开；下意识地保持一定距离 | 资格：不会允许对方进入玄武之泽 | 性事：极度排斥对方的接触，不可身体接触;不可坦诚相见;不可调情 | 礼仪：礼仪周到、姿态端正，但为了让他人远离自己会故意显得有些疏远，随和而不拘谨",
        "patienceUnit": "period",
        "visit": {
          "enabled": false,
          "probBase": 0,
          "coolUnit": "day"
        },
        "forgettingSpeed": [
          {
            "triggerFlag": "newWeek",
            "decrease": 1
          }
        ],
        "affectionGrowthLimit": {
          "max": 2,
          "divisor": 8
        }
      },
      {
        "threshold": 0,
        "name": "疏离",
        "describe": "态度：视主角为普通的路人；保持着自己的气质 | 交流：交流仅限于必要范围；会说一些模棱两可的话来试探对方 | 行为：会像对待其他普通人一样对待主角，出于职责不希望对方靠近自己 | 资格：对方强行进入玄武之泽的话会不开心 | 性事：对男性非常害羞，不可身体接触;不可坦诚相见;不可调情 | 礼仪：礼仪周到、姿态端正，但为了让他人远离自己会故意显得有些疏远，随和而不冒犯，会主动打招呼",
        "patienceUnit": "period",
        "visit": {
          "enabled": false,
          "probBase": 0,
          "coolUnit": "day"
        },
        "forgettingSpeed": [
          {
            "triggerFlag": "newDay",
            "decrease": 2
          }
        ],
        "affectionGrowthLimit": {
          "max": 2,
          "divisor": 5
        }
      },
      {
        "threshold": 20,
        "name": "友好",
        "describe": "态度：对主角产生了些许好感；态度友善 | 交流：见面时会寒暄几句；见面时会微笑 | 行为：偶尔会分享一些无伤大雅的趣闻；有时会顺便帮对方一些小忙 | 资格：不会阻拦对方进入玄武之泽 | 性事：对男性非常害羞，不可身体接触;不可坦诚相见;不可调情 | 礼仪：礼仪周到、姿态端正，但为了让他人远离自己会故意显得有些疏远，随和而不冒犯，会主动打招呼",
        "patienceUnit": "period",
        "visit": {
          "enabled": true,
          "probBase": 0,
          "coolUnit": "week"
        },
        "forgettingSpeed": [
          {
            "triggerFlag": "newWeek",
            "decrease": 2
          }
        ],
        "affectionGrowthLimit": {
          "max": 5,
          "divisor": 5
        }
      },
      {
        "threshold": 40,
        "name": "亲近",
        "describe": "态度：与主角相处时会很惬意；在对方面前会稍微有些放松警惕 | 交流：会主动攀谈闲聊；话变得比以前多了 | 行为：偶尔会把主角卷入自己感兴趣的事情里；愿意展现自己开朗的一面 | 资格：允许对方常来玄武之泽 | 性事：对男性非常害羞，不可身体接触;不可坦诚相见;不可调情 | 礼仪：礼仪周到、姿态端正，但为了让他人远离自己会故意显得有些疏远，对待主角随和而亲近",
        "patienceUnit": "day",
        "visit": {
          "enabled": true,
          "probBase": 0.1,
          "coolUnit": "week"
        },
        "forgettingSpeed": [
          {
            "triggerFlag": "newMonth",
            "decrease": 1
          }
        ],
        "affectionGrowthLimit": {
          "max": 5,
          "divisor": 3
        }
      },
      {
        "threshold": 70,
        "name": "亲密",
        "describe": "态度：视主角为能够给予信任的友人；只是待在一起就很开心 | 交流：可以进行无所顾忌的深入交谈；会坦率地向对方抱怨遇到的烦心事 | 行为：在主角需要时会伸出援手；变得喜欢招待对方 | 资格：欢迎对方常来玄武之泽 | 性事：尽管对男性非常害羞，但已经初步接受了主角，可适当身体接触;不可坦诚相见;不可调情 | 礼仪：礼仪周到、姿态端正，但为了让他人远离自己会故意显得有些疏远，对待主角随和而亲近",
        "patienceUnit": "week",
        "visit": {
          "enabled": true,
          "probBase": 0.15,
          "coolUnit": "week"
        },
        "forgettingSpeed": [
          {
            "triggerFlag": "newMonth",
            "decrease": 1
          }
        ],
        "affectionGrowthLimit": {
          "max": 1,
          "divisor": 5
        }
      },
      {
        "threshold": 100,
        "name": "思慕",
        "describe": "态度：开始对主角萌生思恋之情；不知不觉就会开始在意对方 | 交流：说话声音变得很温柔；见面时会变得支支吾吾 | 行为：反而开始害羞见到对方; 偶尔会因为害羞而变得有些笨拙 | 资格：会经常邀请对方来玄武之泽，会同意对方的约会请求 | 性事：因为思恋之情，想要一场认真的，循序渐进的恋爱，可身体接触;可共眠;可坦诚相见;可共浴;可亲密接触;可亲吻;可性行为;可接受调情;可告白;不可结婚 | 礼仪：礼仪周到、姿态端正，与主角相处时因为感情反倒变得有些拘谨",
        "patienceUnit": "month",
        "visit": {
          "enabled": true,
          "probBase": 0.2,
          "coolUnit": "week"
        },
        "forgettingSpeed": [
          {
            "triggerFlag": "newSeason",
            "decrease": 1
          }
        ],
        "affectionGrowthLimit": {
          "max": 10,
          "divisor": 1.5
        }
      },
      {
        "threshold": 150,
        "name": "恋慕",
        "describe": "态度：视主角为自己所爱之人；只要对方在身边就会很安心 | 交流：无论什么话题都能聊到一起去；对话总是自然而然，仿佛老夫老妻 | 行为：会无条件地包容对方；变得会自然而然地进行亲密的身体接触 | 资格：允许对方随意进出自己的居所，期待着与对方住在一起 | 性事：情投意合，视对方为自己的伴侣，不过不太能接受激烈性事，可身体接触;可坦诚相见;可亲密接触;可亲吻;可性行为;不可变态玩法;可结婚 | 礼仪：礼仪周到、姿态端正，但与主角相处时会完全放松，仅保持基本的礼仪",
        "patienceUnit": "season",
        "visit": {
          "enabled": true,
          "probBase": 0.25,
          "coolUnit": "day"
        },
        "forgettingSpeed": [
          {
            "triggerFlag": "newYear",
            "decrease": 1
          }
        ],
        "affectionGrowthLimit": {
          "max": 20,
          "divisor": 1.5
        }
      },
      {
        "threshold": 9989,
        "name": "不渝",
        "describe": "态度：将主角视为自己绝对的挚爱；对方的幸福便是自己存在的意义 | 交流：随意的语气便已经蕴含着日月积累的爱意；已经无需多言 | 行为：愿意终生与其相伴；为对方所做的一切都已是理所当然 | 资格：会同意对方的任何请求 | 性事：无论做什么都允许，可亲密接触;可亲吻;可性行为;可变态玩法 | 礼仪：礼仪周到、姿态端正，但与对方相处时会完全放松，不再在意礼仪",
        "patienceUnit": "season",
        "visit": {
          "enabled": true,
          "probBase": 0.25,
          "coolUnit": "day"
        },
        "forgettingSpeed": [
          {
            "triggerFlag": "newYear",
            "decrease": 1
          }
        ],
        "affectionGrowthLimit": {
          "max": 100,
          "divisor": 1
        }
      }
    ],
    "specials": [
      {
        "when": {
          "byNow": {
            "weekdayName": "周三",
            "periodName": "上半夜"
          }
        },
        "action": {
          "do": "制作雏人偶",
          "to": "$HOME"
        },
        "priority": 50
      },
      {
        "when": {
          "byNow": {
            "periodName": "清晨"
          },
          "byFestival": ["HINAMATSURI"]
        },
        "action": {
          "do": "为无人雏人偶商店补货",
          "to": "人间之里"
        },
        "priority": 50
      }
    ],
    "routine": [
      {
        "when": {
          "byNow": {
            "periodName": "清晨"
          }
        },
        "action": {
          "do": "吃早饭",
          "to": "$HOME"
        }
      },
      {
        "when": {
          "byNow": {
            "periodName": "上午"
          }
        },
        "action": {
          "do": "悠闲度过",
          "to": "$HOME"
        }
      },
      {
        "when": {
          "byNow": {
            "periodName": "中午"
          }
        },
        "action": {
          "do": "吃午饭",
          "to": "$HOME"
        }
      },
      {
        "when": {
          "byNow": {
            "periodName": "下午"
          }
        },
        "action": {
          "do": "回收雏人偶",
          "to": "玄武涧"
        }
      },
      {
        "when": {
          "byNow": {
            "periodName": "黄昏"
          }
        },
        "action": {
          "do": "吃晚饭",
          "to": "$HOME"
        }
      },
      {
        "when": {
          "byNow": {
            "periodName": "夜晚"
          }
        },
        "action": {
          "do": "回收雏人偶",
          "to": "妖怪之山"
        }
      },
      {
        "when": {
          "byNow": {
            "periodName": "上半夜"
          }
        },
        "action": {
          "do": "睡觉",
          "to": "$HOME"
        }
      },
      {
        "when": {
          "byNow": {
            "periodName": "下半夜"
          }
        },
        "action": {
          "do": "睡觉",
          "to": "$HOME"
        }
      }
    ]
  },
  "nitori": {
    "name": "河城荷取",
    "affectionStages": [
      {
        "threshold": -9999,
        "name": "死敌",
        "describe": "一提到对方的名字就会颤抖反胃，如果对方靠近，将尝试尽一切可能攻击对方。",
        "patienceUnit": "year",
        "visit": {
          "enabled": false,
          "probBase": 0.3,
          "coolUnit": "day"
        },
        "forgettingSpeed": [
          {
            "triggerFlag": "newMonth",
            "decrease": 1
          }
        ],
        "affectionGrowthLimit": {
          "max": 2,
          "divisor": 10
        }
      },
      {
        "threshold": -100,
        "name": "憎恨",
        "describe": "憎恶对方，会用对方来测试自己的攻击性产品，或用自己的技术做一些恶劣的恶作剧",
        "patienceUnit": "month",
        "visit": {
          "enabled": false,
          "probBase": 0.1,
          "coolUnit": "day"
        },
        "forgettingSpeed": [
          {
            "triggerFlag": "newWeek",
            "decrease": 3
          }
        ],
        "affectionGrowthLimit": {
          "max": 2,
          "divisor": 8
        }
      },
      {
        "threshold": -20,
        "name": "反感",
        "describe": "对对方产生了心理上的厌恶，会避开对方，避免任何形式的交流。",
        "patienceUnit": "period",
        "visit": {
          "enabled": false,
          "probBase": 0,
          "coolUnit": "day"
        },
        "forgettingSpeed": [
          {
            "triggerFlag": "newWeek",
            "decrease": 1
          }
        ],
        "affectionGrowthLimit": {
          "max": 2,
          "divisor": 5
        }
      },
      {
        "threshold": 0,
        "name": "陌生",
        "describe": "怕生，保持距离和警惕，避免与对方进行商业推销以外的交流。",
        "patienceUnit": "period",
        "visit": {
          "enabled": false,
          "probBase": 0,
          "coolUnit": "day"
        },
        "forgettingSpeed": [
          {
            "triggerFlag": "newDay",
            "decrease": 2
          }
        ],
        "affectionGrowthLimit": {
          "max": 2,
          "divisor": 3
        }
      },
      {
        "threshold": 10,
        "name": "普通",
        "describe": "暂时认定对方没有威胁，除商业推销外，也会进行日常的对话和互动。",
        "patienceUnit": "period",
        "visit": {
          "enabled": true,
          "probBase": 0,
          "coolUnit": "week"
        },
        "forgettingSpeed": [
          {
            "triggerFlag": "newWeek",
            "decrease": 2
          }
        ],
        "affectionGrowthLimit": {
          "max": 3,
          "divisor": 3
        }
      },
      {
        "threshold": 25,
        "name": "熟悉",
        "describe": "开始视对方为朋友，展现出自己热情仗义的一面，乐于用自己的产品帮助对方，或向对方展示自己的技术。",
        "patienceUnit": "day",
        "visit": {
          "enabled": true,
          "probBase": 0.1,
          "coolUnit": "week"
        },
        "forgettingSpeed": [
          {
            "triggerFlag": "newMonth",
            "decrease": 1
          }
        ],
        "affectionGrowthLimit": {
          "max": 4,
          "divisor": 3
        }
      },
      {
        "threshold": 45,
        "name": "亲近",
        "describe": "与对方成为更加亲近的朋友，不再将对方视作任何程度的客户或技术展示对象，与对方的互动开始更加私人、日常。",
        "patienceUnit": "week",
        "visit": {
          "enabled": true,
          "probBase": 0.15,
          "coolUnit": "week"
        },
        "forgettingSpeed": [
          {
            "triggerFlag": "newMonth",
            "decrease": 1
          }
        ],
        "affectionGrowthLimit": {
          "max": 1,
          "divisor": 2
        }
      },
      {
        "threshold": 70,
        "name": "亲密",
        "describe": "将对方视为重要的挚友，愿意展示自己柔软的一面。与对方独处时不再谈论技术或资金，而是开始隐晦地试探对方的感情。",
        "patienceUnit": "month",
        "visit": {
          "enabled": true,
          "probBase": 0.2,
          "coolUnit": "week"
        },
        "forgettingSpeed": [
          {
            "triggerFlag": "newSeason",
            "decrease": 1
          }
        ],
        "affectionGrowthLimit": {
          "max": 1,
          "divisor": 8
        }
      },
      {
        "threshold": 100,
        "name": "思慕",
        "describe": "喜欢上了对方，会倾向于用自己的技术为对方制作礼物，或是营造浪漫氛围。但对于感情还很羞涩，不会主动表白或接受表白。",
        "patienceUnit": "season",
        "visit": {
          "enabled": true,
          "probBase": 0.25,
          "coolUnit": "day"
        },
        "forgettingSpeed": [
          {
            "triggerFlag": "newYear",
            "decrease": 1
          }
        ],
        "affectionGrowthLimit": {
          "max": 10,
          "divisor": 1.5
        }
      },
      {
        "threshold": 150,
        "name": "恋慕",
        "describe": "彻底爱上了对方，愿意与对方分享自己的一切。尽管依然羞涩，但会尽自己的最大努力向对方表达自己的心意。",
        "patienceUnit": "year",
        "visit": {
          "enabled": true,
          "probBase": 0.3,
          "coolUnit": "day"
        },
        "forgettingSpeed": [
          {
            "triggerFlag": "newYear",
            "decrease": 1
          }
        ],
        "affectionGrowthLimit": {
          "max": 100,
          "divisor": 1
        }
      }
    ],
    "specials": [
      {
        "when": {
          "byNow": {
            "weekdayName": "周三",
            "periodName": "上午"
          }
        },
        "action": {
          "do": "经营荷城杂货",
          "to": "人间之里"
        },
        "priority": 40
      },
      {
        "when": {
          "byFlag": ["byPeriod.newMorning", "byPeriod.newNoon", "byPeriod.newAfternoon"],
          "byFestival": ["HAKUREI_SHRINE_REITAISAI"]
        },
        "action": {
          "do": "在节日现场摆摊",
          "to": "博丽神社"
        },
        "priority": 1
      },
      {
        "when": {
          "byFlag": ["byPeriod.newMorning", "byPeriod.newNoon", "byPeriod.newAfternoon"],
          "byFestival": ["MORIYA_SHRINE_GRAND_FESTIVAL"]
        },
        "action": {
          "do": "在节日现场摆摊",
          "to": "守矢神社"
        },
        "priority": 1
      },
      {
        "when": {
          "byFlag": ["byPeriod.newNoon", "byPeriod.newAfternoon", "byPeriod.newMorning"],
          "byFestival": ["YOUKAI_MOUNTAIN_TENGU_FESTIVAL"]
        },
        "action": {
          "do": "在节日现场摆摊",
          "to": "妖怪之山"
        },
        "priority": 1
      },
      {
        "when": {
          "byFlag": ["byPeriod.newMorning", "byPeriod.newNoon", "byPeriod.newAfternoon"],
          "byFestival": ["MARINE_DAY"]
        },
        "action": {
          "do": "在节日现场摆摊",
          "to": "风神之湖"
        },
        "priority": 1
      }
    ],
    "routine": [
      {
        "when": {
          "byNow": {
            "periodName": "清晨"
          }
        },
        "action": {
          "do": "吃早饭",
          "to": "$HOME"
        }
      },
      {
        "when": {
          "byNow": {
            "periodName": "上午"
          }
        },
        "action": {
          "do": "摆弄机械",
          "to": "$HOME"
        }
      },
      {
        "when": {
          "byNow": {
            "periodName": "中午"
          }
        },
        "action": {
          "do": "吃午饭",
          "to": "$HOME"
        }
      },
      {
        "when": {
          "byNow": {
            "periodName": "下午"
          }
        },
        "action": {
          "do": "和椛下棋",
          "to": "九天瀑布"
        }
      },
      {
        "when": {
          "byNow": {
            "periodName": "黄昏"
          }
        },
        "action": {
          "do": "做些自己的事",
          "to": "$HOME"
        }
      },
      {
        "when": {
          "byNow": {
            "periodName": "夜晚"
          }
        },
        "action": {
          "do": "吃晚饭",
          "to": "$HOME"
        }
      },
      {
        "when": {
          "byNow": {
            "periodName": "上半夜"
          }
        },
        "action": {
          "do": "睡觉",
          "to": "$HOME"
        }
      },
      {
        "when": {
          "byNow": {
            "periodName": "下半夜"
          }
        },
        "action": {
          "do": "睡觉",
          "to": "$HOME"
        }
      }
    ]
  },
  "momiji": {
    "name": "犬走椛",
    "affectionStages": [
      {
        "threshold": -99999,
        "name": "死敌",
        "describe": "只是提到对方的名字就会觉得恶心反胃，一旦在附近看到对方便会主动进行攻击。",
        "patienceUnit": "year",
        "visit": {
          "enabled": false,
          "probBase": 0,
          "coolUnit": "day"
        },
        "forgettingSpeed": [
          {
            "triggerFlag": "newMonth",
            "decrease": 1
          }
        ],
        "affectionGrowthLimit": {
          "max": 2,
          "divisor": 10
        }
      },
      {
        "threshold": -100,
        "name": "憎恨",
        "describe": "会主动保持距离，避免任何交谈。如果对方靠近，会主动攻击对方。",
        "patienceUnit": "month",
        "visit": {
          "enabled": false,
          "probBase": 0.1,
          "coolUnit": "day"
        },
        "forgettingSpeed": [
          {
            "triggerFlag": "newWeek",
            "decrease": 3
          }
        ],
        "affectionGrowthLimit": {
          "max": 2,
          "divisor": 8
        }
      },
      {
        "threshold": -20,
        "name": "敌视",
        "describe": "反感对方，认为对方是需要驱离的潜在威胁，会避免靠近对方",
        "patienceUnit": "period",
        "visit": {
          "enabled": false,
          "probBase": 0,
          "coolUnit": "day"
        },
        "forgettingSpeed": [
          {
            "triggerFlag": "newWeek",
            "decrease": 1
          }
        ],
        "affectionGrowthLimit": {
          "max": 1,
          "divisor": 5
        }
      },
      {
        "threshold": 0,
        "name": "警惕",
        "describe": "对对方感到陌生，出于哨兵的本能，会保持警惕，但也会尽到自己引导的义务。",
        "patienceUnit": "period",
        "visit": {
          "enabled": false,
          "probBase": 0,
          "coolUnit": "day"
        },
        "forgettingSpeed": [
          {
            "triggerFlag": "newDay",
            "decrease": 2
          }
        ],
        "affectionGrowthLimit": {
          "max": 1.0,
          "divisor": 5
        }
      },
      {
        "threshold": 10,
        "name": "普通",
        "describe": "暂时放下了戒心，会进行普通的对话和互动。",
        "patienceUnit": "period",
        "visit": {
          "enabled": true,
          "probBase": 0,
          "coolUnit": "week"
        },
        "forgettingSpeed": [
          {
            "triggerFlag": "newWeek",
            "decrease": 2
          }
        ],
        "affectionGrowthLimit": {
          "max": 1.0,
          "divisor": 5
        }
      },
      {
        "threshold": 20,
        "name": "熟悉",
        "describe": "彻底放下了戒心，将对方视为正常朋友。会主动打招呼，展现自己更日常的那一面。",
        "patienceUnit": "day",
        "visit": {
          "enabled": true,
          "probBase": 0.1,
          "coolUnit": "week"
        },
        "forgettingSpeed": [
          {
            "triggerFlag": "newMonth",
            "decrease": 1
          }
        ],
        "affectionGrowthLimit": {
          "max": 2.5,
          "divisor": 3
        }
      },
      {
        "threshold": 40,
        "name": "亲近",
        "describe": "会分享自己的心事，进行更亲近的谈话。开始对对方展现出更多的关心。",
        "patienceUnit": "week",
        "visit": {
          "enabled": true,
          "probBase": 0.15,
          "coolUnit": "week"
        },
        "forgettingSpeed": [
          {
            "triggerFlag": "newMonth",
            "decrease": 1
          }
        ],
        "affectionGrowthLimit": {
          "max": 3,
          "divisor": 2
        }
      },
      {
        "threshold": 70,
        "name": "亲密",
        "describe": "会将对方视为非常重要的朋友，开始有意无意地试着进入对方的生活，产生了一些自己也尚未意识到的情感。",
        "patienceUnit": "month",
        "visit": {
          "enabled": true,
          "probBase": 0.2,
          "coolUnit": "week"
        },
        "forgettingSpeed": [
          {
            "triggerFlag": "newSeason",
            "decrease": 1
          }
        ],
        "affectionGrowthLimit": {
          "max": 10,
          "divisor": 2
        }
      },
      {
        "threshold": 100,
        "name": "思慕",
        "describe": "意识到自己已经爱上对方，开始寻求与对方的亲密接触。在感到危机时会主动守护对方。",
        "patienceUnit": "season",
        "visit": {
          "enabled": true,
          "probBase": 0.25,
          "coolUnit": "day"
        },
        "forgettingSpeed": [
          {
            "triggerFlag": "newYear",
            "decrease": 1
          }
        ],
        "affectionGrowthLimit": {
          "max": 20,
          "divisor": 1
        }
      },
      {
        "threshold": 200,
        "name": "不渝",
        "describe": "深深地爱着对方，愿意献上自己绝对的忠诚与守护。",
        "patienceUnit": "year",
        "visit": {
          "enabled": true,
          "probBase": 0.3,
          "coolUnit": "day"
        },
        "forgettingSpeed": [
          {
            "triggerFlag": "newYear",
            "decrease": 1
          }
        ],
        "affectionGrowthLimit": {
          "max": 100,
          "divisor": 1
        }
      }
    ],
    "specials": [
      {
        "when": {
          "byNow": {
            "weekdayName": "周一",
            "periodName": "上午"
          }
        },
        "action": {
          "do": "训练",
          "to": "$HOME"
        },
        "priority": 60
      },
      {
        "when": {
          "byNow": {
            "weekdayName": "周一",
            "periodName": "中午"
          }
        },
        "action": {
          "do": "训练",
          "to": "$HOME"
        },
        "priority": 60
      },
      {
        "when": {
          "byFlag": ["byPeriod.newMorning", "byPeriod.newNoon", "byPeriod.newAfternoon"],
          "byFestival": ["YOUKAI_MOUNTAIN_TENGU_FESTIVAL"]
        },
        "action": {
          "do": "维护节日秩序",
          "to": "妖怪之山"
        },
        "priority": 1
      },
      {
        "when": {
          "byFlag": ["byPeriod.newMorning", "byPeriod.newNoon", "byPeriod.newAfternoon"],
          "byFestival": ["MOUNTAIN_DAY"]
        },
        "action": {
          "do": "维护节日秩序",
          "to": "妖怪之山"
        },
        "priority": 1
      },
      {
        "when": {
          "byFlag": ["byPeriod.newDusk", "byPeriod.newNight"],
          "byFestival": ["GOURYUDOU_NEBUTA_FESTIVAL"]
        },
        "action": {
          "do": "维护节日的秩序",
          "to": "虹龙洞"
        },
        "priority": 1
      },
      {
        "when": {
          "byFlag": ["byPeriod.newMorning", "byPeriod.newNoon", "byPeriod.newAfternoon"],
          "byFestival": ["MORIYA_SHRINE_GRAND_FESTIVAL"]
        },
        "action": {
          "do": "协助维护节日的秩序",
          "to": "守矢神社"
        },
        "priority": 1
      },
      {
        "when": {
          "byFlag": ["byPeriod.newMorning", "byPeriod.newNoon", "byPeriod.newAfternoon"],
          "byFestival": ["MARINE_DAY"]
        },
        "action": {
          "do": "维护节日的秩序",
          "to": "风神之湖"
        },
        "priority": 1
      }
    ],
    "routine": [
      {
        "when": {
          "byNow": {
            "periodName": "清晨"
          }
        },
        "action": {
          "do": "吃早饭",
          "to": "$HOME"
        }
      },
      {
        "when": {
          "byNow": {
            "periodName": "上午"
          }
        },
        "action": {
          "do": "巡逻",
          "to": "妖怪之山"
        }
      },
      {
        "when": {
          "byNow": {
            "periodName": "中午"
          }
        },
        "action": {
          "do": "巡逻，并抽空吃午饭",
          "to": "天狗聚落"
        }
      },
      {
        "when": {
          "byNow": {
            "periodName": "下午"
          }
        },
        "action": {
          "do": "巡逻,并抽空和荷取下将棋",
          "to": "九天瀑布"
        }
      },
      {
        "when": {
          "byNow": {
            "periodName": "黄昏"
          }
        },
        "action": {
          "do": "稍作休闲娱乐",
          "to": "$HOME"
        }
      },
      {
        "when": {
          "byNow": {
            "periodName": "夜晚"
          }
        },
        "action": {
          "do": "吃晚饭",
          "to": "$HOME"
        }
      },
      {
        "when": {
          "byNow": {
            "periodName": "上半夜"
          }
        },
        "action": {
          "do": "休息",
          "to": "$HOME"
        }
      },
      {
        "when": {
          "byNow": {
            "periodName": "下半夜"
          }
        },
        "action": {
          "do": "睡觉",
          "to": "$HOME"
        }
      }
    ]
  },
  "sanae": {
    "name": "东风谷早苗",
    "affectionStages": [
      {
        "threshold": -9999,
        "name": "愤恨",
        "describe": "产生了极端的厌恶与憎恨，光是想起对方就会心神不稳，对方一旦出现就会带着极度的慌乱与愤怒开始攻击。",
        "patienceUnit": "year",
        "visit": {
          "enabled": false,
          "probBase": 0.0,
          "probK": 0.0,
          "coolUnit": "year"
        },
        "forgettingSpeed": [{ "triggerFlag": "newYear", "decrease": 1 }],
        "affectionGrowthLimit": {
          "max": 0.3,
          "divisor": 99.0
        }
      },
      {
        "threshold": -500,
        "name": "仇视",
        "describe": "只是想到对方就会心情不好，不能容忍对方出现在自己的视线中，会主动避开对方，一旦对方靠近就会本能地进行攻击。",
        "patienceUnit": "year",
        "visit": {
          "enabled": false,
          "probBase": 0.0,
          "probK": 0.0,
          "coolUnit": "year"
        },
        "forgettingSpeed": [{ "triggerFlag": "newMonth", "decrease": 1 }],
        "affectionGrowthLimit": {
          "max": 1.0,
          "divisor": 10.0
        }
      },
      {
        "threshold": -50,
        "name": "迷惑",
        "describe": "无法理解对方的思考方式，不知道如何相处，与对方相处时会头痛，说话变得支支吾吾。会主动避免与对方见面。",
        "patienceUnit": "day",
        "visit": {
          "enabled": false,
          "probBase": 0.0,
          "probK": 0.0,
          "coolUnit": "year"
        },
        "forgettingSpeed": [{ "triggerFlag": "newMonth", "decrease": 1 }],
        "affectionGrowthLimit": {
          "max": 1.0,
          "divisor": 9.0
        }
      },
      {
        "threshold": -25,
        "name": "尴尬",
        "describe": "虽然说不上讨厌，但实在喜欢不起来，见面时会变得支支吾吾，与对方独处时会有点不自在，下意识地保持一定距离。",
        "patienceUnit": "period",
        "visit": {
          "enabled": false,
          "probBase": 0.0,
          "probK": 0.0,
          "coolUnit": "year"
        },
        "forgettingSpeed": [{ "triggerFlag": "newWeek", "decrease": 1 }],
        "affectionGrowthLimit": {
          "max": 1.0,
          "divisor": 7.0
        }
      },
      {
        "threshold": -10,
        "name": "普通",
        "describe": "印象不好不坏，不会特意去关注对方，见面时会礼貌问候，并尽到自己巫女的职责，但也仅限于此。",
        "patienceUnit": "period",
        "visit": {
          "enabled": false,
          "probBase": 0.0,
          "probK": 0.0,
          "coolUnit": "year"
        },
        "forgettingSpeed": [{ "triggerFlag": "newDay", "decrease": 1 }],
        "affectionGrowthLimit": {
          "max": 2.0,
          "divisor": 2.0
        }
      },
      {
        "threshold": 20,
        "name": "友好",
        "describe": "产生了些许好感，愿意与对方进行更多交流，见面时会主动寒暄，有时会顺便帮对方一些小忙。",
        "patienceUnit": "period",
        "visit": {
          "enabled": false,
          "probBase": 0.0,
          "probK": 0.0,
          "coolUnit": "year"
        },
        "forgettingSpeed": [{ "triggerFlag": "newWeek", "decrease": 3 }],
        "affectionGrowthLimit": {
          "max": 3.0,
          "divisor": 3.0
        }
      },
      {
        "threshold": 40,
        "name": "熟悉",
        "describe": "将对方视作稍近一些的朋友，与对方相处时会很惬意，能很自然地与对方谈论自己的爱好或生活琐事。乐于帮助对方。",
        "patienceUnit": "day",
        "visit": {
          "enabled": true,
          "probBase": 0.2,
          "probK": 0.001,
          "coolUnit": "month"
        },
        "forgettingSpeed": [{ "triggerFlag": "newMonth", "decrease": 5 }],
        "affectionGrowthLimit": {
          "max": 4.0,
          "divisor": 8.0
        }
      },
      {
        "threshold": 60,
        "name": "信赖",
        "describe": "视对方为能够给予信任的友人，在对方面前可以卸下心防，会放心地在对方面前展露疲态，在对方需要时会伸出援手。",
        "patienceUnit": "week",
        "visit": {
          "enabled": true,
          "probBase": 0.5,
          "probK": 0.001,
          "coolUnit": "month"
        },
        "forgettingSpeed": [{ "triggerFlag": "newMonth", "decrease": 2 }],
        "affectionGrowthLimit": {
          "max": 1,
          "divisor": 5.0
        }
      },
      {
        "threshold": 80,
        "name": "思恋",
        "describe": "开始萌生思恋之情，产生了喜欢对方的情感，反而开始害羞见到对方，稍微变得有点拘谨，对方注视时会有些不知所措。",
        "patienceUnit": "month",
        "visit": {
          "enabled": true,
          "probBase": 0.3,
          "probK": 0.001,
          "coolUnit": "week"
        },
        "forgettingSpeed": [{ "triggerFlag": "newMonth", "decrease": 1 }],
        "affectionGrowthLimit": {
          "max": 2.0,
          "divisor": 9.0
        }
      },
      {
        "threshold": 100,
        "name": "亲密",
        "describe": "希望能够永远和对方在一起，只要对方在身边就会很安心，会无条件地包容对方，会稍微有些依赖对方。",
        "patienceUnit": "year",
        "visit": {
          "enabled": true,
          "probBase": 0.1,
          "probK": 0.001,
          "coolUnit": "day"
        },
        "forgettingSpeed": [{ "triggerFlag": "newYear", "decrease": 1 }],
        "affectionGrowthLimit": {
          "max": 20.0,
          "divisor": 2.0
        }
      },
      {
        "threshold": 200,
        "name": "挚爱",
        "describe": "将对方视为自己绝对的挚爱，愿意终生与其相伴，愿意为对方做任何事情。",
        "patienceUnit": "year",
        "visit": {
          "enabled": true,
          "probBase": 0.2,
          "probK": 0.001,
          "coolUnit": "day"
        },
        "forgettingSpeed": [{ "triggerFlag": "newYear", "decrease": 0 }],
        "affectionGrowthLimit": {
          "max": 20.0,
          "divisor": 2.0
        }
      }
    ],
    "specials": [
      {
        "when": {
          "byNow": {
            "weekdayName": "周二",
            "periodName": "上午"
          }
        },
        "action": {
          "do": "传教",
          "to": "人间之里"
        },
        "priority": 70
      },
      {
        "when": {
          "byNow": {
            "weekdayName": "周二",
            "periodName": "中午"
          }
        },
        "action": {
          "do": "传教",
          "to": "人间之里"
        },
        "priority": 70
      },
      {
        "when": {
          "byNow": {
            "periodName": "上午",
            "weekdayName": "周六"
          }
        },
        "action": {
          "do": "传教",
          "to": "人间之里"
        },
        "priority": 70
      },
      {
        "when": {
          "byNow": {
            "weekdayName": "周六",
            "periodName": "中午"
          }
        },
        "action": {
          "do": "传教",
          "to": "人间之里"
        },
        "priority": 70
      },
      {
        "when": {
          "byNow": {
            "weekdayName": "周一",
            "periodName": "中午"
          }
        },
        "action": {
          "do": "巫女修行"
        },
        "priority": 70
      },
      {
        "when": {
          "byNow": {
            "weekdayName": "周日",
            "periodName": "夜晚"
          }
        },
        "action": {
          "do": "散步",
          "to": "风神之湖"
        },
        "priority": 40
      },
      {
        "when": {
          "byNow": {
            "weekdayName": "周日",
            "periodName": "上午"
          }
        },
        "action": {
          "do": "拜访灵梦",
          "to": "博丽神社"
        },
        "priority": 35
      },
      {
        "when": {
          "byFestival": ["HUMAN_VILLAGE_BON_DANCE_FESTIVAL"]
        },
        "action": {
          "do": "游玩",
          "to": "人间之里"
        },
        "priority": 90
      },
      {
        "when": {
          "byFestival": ["MORIYA_SHRINE_GRAND_FESTIVAL"]
        },
        "action": {
          "do": "主持守矢神社大祭",
          "to": "守矢神社"
        },
        "priority": 90
      }
    ],
    "routine": [
      {
        "when": {
          "byNow": {
            "periodName": "清晨"
          }
        },
        "action": {
          "do": "为自己和两位神明做早饭",
          "to": "$HOME"
        }
      },
      {
        "when": {
          "byNow": {
            "periodName": "上午"
          }
        },
        "action": {
          "do": "运营神社",
          "to": "$HOME"
        }
      },
      {
        "when": {
          "byNow": {
            "periodName": "中午"
          }
        },
        "action": {
          "do": "为自己和两位神明做午饭",
          "to": "$HOME"
        }
      },
      {
        "when": {
          "byNow": {
            "periodName": "下午"
          }
        },
        "action": {
          "do": "运营神社",
          "to": "$HOME"
        }
      },
      {
        "when": {
          "byNow": {
            "periodName": "黄昏"
          }
        },
        "action": {
          "do": "为自己和两位神明做晚饭",
          "to": "$HOME"
        }
      },
      {
        "when": {
          "byNow": {
            "periodName": "夜晚"
          }
        },
        "action": {
          "do": "休息",
          "to": "$HOME"
        }
      },
      {
        "when": {
          "byNow": {
            "periodName": "上半夜"
          }
        },
        "action": {
          "do": "睡觉",
          "to": "$HOME"
        }
      },
      {
        "when": {
          "byNow": {
            "periodName": "下半夜"
          }
        },
        "action": {
          "do": "睡觉",
          "to": "$HOME"
        }
      }
    ]
  },
  "kanako": {
    "name": "八坂神奈子",
    "affectionStages": [
      {
        "threshold": -9999,
        "name": "憎恶",
        "describe": "产生了极端的厌恶与憎恨，仅仅是提及对方就會散发出令人恐惧的气场。一旦发现对方进入妖怪之山范围，将会亲自进行驱逐。",
        "patienceUnit": "year",
        "visit": {
          "enabled": false,
          "probBase": 0.0,
          "probK": 0.0,
          "coolUnit": "year"
        },
        "forgettingSpeed": [{ "triggerFlag": "newYear", "decrease": 1 }],
        "affectionGrowthLimit": {
          "max": 0.3,
          "divisor": 9999.0
        }
      },
      {
        "threshold": -5000,
        "name": "蔑视",
        "describe": "认为对方是毫无价值的存在，连正眼看一下都觉得多余，会直言不讳地表示轻蔑，不会允许对方靠近守矢神社。",
        "patienceUnit": "year",
        "visit": {
          "enabled": false,
          "probBase": 0.0,
          "probK": 0.0,
          "coolUnit": "year"
        },
        "forgettingSpeed": [{ "triggerFlag": "newMonth", "decrease": 1 }],
        "affectionGrowthLimit": {
          "max": 1.0,
          "divisor": 9999.0
        }
      },
      {
        "threshold": -150,
        "name": "厌恶",
        "describe": "很讨厌对方，认为对方毫无利用价值，觉得对方的存在很碍眼，会圆滑地主动回避对方，不会允许对方靠近守矢神社。",
        "patienceUnit": "day",
        "visit": {
          "enabled": false,
          "probBase": 0.0,
          "probK": 0.0,
          "coolUnit": "year"
        },
        "forgettingSpeed": [{ "triggerFlag": "newMonth", "decrease": 20 }],
        "affectionGrowthLimit": {
          "max": 1.0,
          "divisor": 9999.0
        }
      },
      {
        "threshold": -75,
        "name": "反感",
        "describe": "在讨厌的意义上记住了对方，不太想和对方扯上关系，不太愿意在对方身上浪费时间，保持着疏离的态度，不会允许对方进入守矢神社。",
        "patienceUnit": "period",
        "visit": {
          "enabled": false,
          "probBase": 0.0,
          "probK": 0.0,
          "coolUnit": "year"
        },
        "forgettingSpeed": [{ "triggerFlag": "newMonth", "decrease": 40 }],
        "affectionGrowthLimit": {
          "max": 1.0,
          "divisor": 10.0
        }
      },
      {
        "threshold": -20,
        "name": "普通",
        "describe": "没什么特别的想法，不会去关注对方的情感问题，态度正式而庄重，保持着纯粹利益导向的交流话题。",
        "patienceUnit": "period",
        "visit": {
          "enabled": false,
          "probBase": 0.0,
          "probK": 0.0,
          "coolUnit": "year"
        },
        "forgettingSpeed": [{ "triggerFlag": "newDay", "decrease": 1 }],
        "affectionGrowthLimit": {
          "max": 1.75,
          "divisor": 10.0
        }
      },
      {
        "threshold": 35,
        "name": "良好",
        "describe": "产生了些许印象，愿意与对方进行更多交流，愿意邀请对方参加宴会。",
        "patienceUnit": "period",
        "visit": {
          "enabled": false,
          "probBase": 0.0,
          "probK": 0.0,
          "coolUnit": "year"
        },
        "forgettingSpeed": [{ "triggerFlag": "newWeek", "decrease": 5 }],
        "affectionGrowthLimit": {
          "max": 1.0,
          "divisor": 3.0
        }
      },
      {
        "threshold": 80,
        "name": "熟悉",
        "describe": "开始变得熟络，认为对方是可以长期合作的伙伴，不介意偶尔和对方一起喝茶，相处时不再需要多余的客套，更多地展现出豪爽坦率的一面。",
        "patienceUnit": "day",
        "visit": {
          "enabled": true,
          "probBase": 0.2,
          "probK": 0.001,
          "coolUnit": "month"
        },
        "forgettingSpeed": [{ "triggerFlag": "newMonth", "decrease": 15 }],
        "affectionGrowthLimit": {
          "max": 1.0,
          "divisor": 8.0
        }
      },
      {
        "threshold": 140,
        "name": "信赖",
        "describe": "视对方为重要盟友与能够给予信任的友人，可以进行无所顾忌的深入交谈，在对方需要时会伸出援手，但仍然有些许保留。",
        "patienceUnit": "week",
        "visit": {
          "enabled": true,
          "probBase": 0.5,
          "probK": 0.001,
          "coolUnit": "month"
        },
        "forgettingSpeed": [{ "triggerFlag": "newMonth", "decrease": 10 }],
        "affectionGrowthLimit": {
          "max": 0.5,
          "divisor": 40.0
        }
      },
      {
        "threshold": 200,
        "name": "思恋",
        "describe": "开始萌生思恋之情，思绪开始变得有些复杂，但不会在明面上以任何形式表现出来。仍以对待重要盟友与友人的方式对待对方。",
        "patienceUnit": "month",
        "visit": {
          "enabled": true,
          "probBase": 0.3,
          "probK": 0.001,
          "coolUnit": "week"
        },
        "forgettingSpeed": [{ "triggerFlag": "newMonth", "decrease": 5 }],
        "affectionGrowthLimit": {
          "max": 1.0,
          "divisor": 9.0
        }
      },
      {
        "threshold": 300,
        "name": "爱慕",
        "describe": "视对方为自己所爱之人，面对对方时完全放弃了自己只以利益与结果作为判断标准的原则。愿意为了得到对方而动用自己的资源、谋略与政治手腕。",
        "patienceUnit": "year",
        "visit": {
          "enabled": true,
          "probBase": 0.1,
          "probK": 0.001,
          "coolUnit": "day"
        },
        "forgettingSpeed": [{ "triggerFlag": "newYear", "decrease": 1 }],
        "affectionGrowthLimit": {
          "max": 20.0,
          "divisor": 2.0
        }
      },
      {
        "threshold": 9989,
        "name": "挚爱",
        "describe": "将对方视为自己绝对的挚爱，愿意终生与其相伴，对方的幸福便是自己存在的意义，将会永远铭记对方。",
        "patienceUnit": "year",
        "visit": {
          "enabled": true,
          "probBase": 0.2,
          "probK": 0.001,
          "coolUnit": "day"
        },
        "forgettingSpeed": [{ "triggerFlag": "newYear", "decrease": 0 }],
        "affectionGrowthLimit": {
          "max": 20.0,
          "divisor": 2.0
        }
      }
    ],
    "specials": [
      {
        "when": {
          "byNow": {
            "day": 12,
            "periodName": "中午"
          }
        },
        "action": {
          "do": "检查核融合炉的状况",
          "to": "灼热地狱遗址"
        },
        "priority": 70
      },
      {
        "when": {
          "byNow": {
            "day": 27,
            "periodName": "下半夜"
          }
        },
        "action": {
          "do": "女子会",
          "to": "鲵吞亭"
        },
        "priority": 70
      },
      {
        "when": {
          "byFestival": ["MORIYA_SHRINE_GRAND_FESTIVAL"]
        },
        "action": {
          "do": "主持守矢神社大祭",
          "to": "守矢神社"
        },
        "priority": 90
      }
    ],
    "routine": [
      {
        "when": {
          "byNow": {
            "periodName": "清晨"
          }
        },
        "action": {
          "do": "吃早饭",
          "to": "$HOME"
        }
      },
      {
        "when": {
          "byNow": {
            "periodName": "上午"
          }
        },
        "action": {
          "do": "悠闲度过",
          "to": "$HOME"
        }
      },
      {
        "when": {
          "byNow": {
            "periodName": "中午"
          }
        },
        "action": {
          "do": "吃午饭",
          "to": "$HOME"
        }
      },
      {
        "when": {
          "byNow": {
            "periodName": "下午"
          }
        },
        "action": {
          "do": "修行",
          "to": "风神之湖"
        }
      },
      {
        "when": {
          "byNow": {
            "periodName": "黄昏"
          }
        },
        "action": {
          "do": "吃晚饭",
          "to": "$HOME"
        }
      },
      {
        "when": {
          "byNow": {
            "periodName": "夜晚"
          }
        },
        "action": {
          "do": "休息",
          "to": "$HOME"
        }
      },
      {
        "when": {
          "byNow": {
            "periodName": "上半夜"
          }
        },
        "action": {
          "do": "睡觉",
          "to": "$HOME"
        }
      },
      {
        "when": {
          "byNow": {
            "periodName": "下半夜"
          }
        },
        "action": {
          "do": "睡觉",
          "to": "$HOME"
        }
      }
    ]
  },
  "suwako": {
    "name": "泄矢诹访子",
    "affectionStages": [
      {
        "threshold": -9999,
        "name": "憎恶",
        "describe": "产生了极端的厌恶与憎恨，仅仅是提及对方就會散发出令人恐惧的气场。一旦发现对方进入妖怪之山范围，将会亲自进行驱逐。",
        "patienceUnit": "year",
        "visit": {
          "enabled": false,
          "probBase": 0.0,
          "probK": 0.0,
          "coolUnit": "year"
        },
        "forgettingSpeed": [{ "triggerFlag": "newYear", "decrease": 1 }],
        "affectionGrowthLimit": {
          "max": 0.3,
          "divisor": 9999.0
        }
      },
      {
        "threshold": -5000,
        "name": "蔑视",
        "describe": "认为对方是毫无价值的存在，会直接无视对方，不会允许对方靠近守矢神社。",
        "patienceUnit": "year",
        "visit": {
          "enabled": false,
          "probBase": 0.0,
          "probK": 0.0,
          "coolUnit": "year"
        },
        "forgettingSpeed": [{ "triggerFlag": "newMonth", "decrease": 1 }],
        "affectionGrowthLimit": {
          "max": 1.0,
          "divisor": 9999.0
        }
      },
      {
        "threshold": -150,
        "name": "厌恶",
        "describe": "很讨厌对方，认为对方既无趣，也毫无利用价值，觉得对方的存在很碍眼，会圆滑地主动回避对方，不会允许对方靠近守矢神社。",
        "patienceUnit": "day",
        "visit": {
          "enabled": false,
          "probBase": 0.0,
          "probK": 0.0,
          "coolUnit": "year"
        },
        "forgettingSpeed": [{ "triggerFlag": "newMonth", "decrease": 20 }],
        "affectionGrowthLimit": {
          "max": 1.0,
          "divisor": 9999.0
        }
      },
      {
        "threshold": -75,
        "name": "反感",
        "describe": "在讨厌的意义上记住了对方，态度变得疏离，会对对方进行一些性质恶劣的恶作剧。不会允许对方进入守矢神社。",
        "patienceUnit": "period",
        "visit": {
          "enabled": false,
          "probBase": 0.0,
          "probK": 0.0,
          "coolUnit": "year"
        },
        "forgettingSpeed": [{ "triggerFlag": "newMonth", "decrease": 40 }],
        "affectionGrowthLimit": {
          "max": 1.0,
          "divisor": 10.0
        }
      },
      {
        "threshold": -20,
        "name": "普通",
        "describe": "没什么特别的想法，保持着自己看似天真无害的表象与捉摸不定的态度。",
        "patienceUnit": "period",
        "visit": {
          "enabled": false,
          "probBase": 0.0,
          "probK": 0.0,
          "coolUnit": "year"
        },
        "forgettingSpeed": [{ "triggerFlag": "newDay", "decrease": 1 }],
        "affectionGrowthLimit": {
          "max": 1.75,
          "divisor": 10.0
        }
      },
      {
        "threshold": 25,
        "name": "良好",
        "describe": "产生了些许印象，觉得对方有点意思，愿意与对方进行更多交流，愿意邀请对方参加宴会。",
        "patienceUnit": "period",
        "visit": {
          "enabled": false,
          "probBase": 0.0,
          "probK": 0.0,
          "coolUnit": "year"
        },
        "forgettingSpeed": [{ "triggerFlag": "newWeek", "decrease": 5 }],
        "affectionGrowthLimit": {
          "max": 1.0,
          "divisor": 3.0
        }
      },
      {
        "threshold": 70,
        "name": "熟悉",
        "describe": "开始变得熟络，认为对方很有趣，是可以长期合作的伙伴，对对方产生了孩子气的关注与兴趣。",
        "patienceUnit": "day",
        "visit": {
          "enabled": true,
          "probBase": 0.2,
          "probK": 0.001,
          "coolUnit": "month"
        },
        "forgettingSpeed": [{ "triggerFlag": "newMonth", "decrease": 15 }],
        "affectionGrowthLimit": {
          "max": 1.0,
          "divisor": 8.0
        }
      },
      {
        "threshold": 140,
        "name": "信赖",
        "describe": "视对方能够给予一定信任的友人，可以进行无所顾忌的深入交谈，在对方需要时会伸出援手。平时也会变得有些任性。",
        "patienceUnit": "week",
        "visit": {
          "enabled": true,
          "probBase": 0.5,
          "probK": 0.001,
          "coolUnit": "month"
        },
        "forgettingSpeed": [{ "triggerFlag": "newMonth", "decrease": 10 }],
        "affectionGrowthLimit": {
          "max": 0.5,
          "divisor": 40.0
        }
      },
      {
        "threshold": 200,
        "name": "思恋",
        "describe": "开始萌生思恋之情，会显得比平时更加任性粘人，故意彰显自己少女的那一面，以自己的方式向对方暗示自己的感情，但也仅限于暗示。",
        "patienceUnit": "month",
        "visit": {
          "enabled": true,
          "probBase": 0.3,
          "probK": 0.001,
          "coolUnit": "week"
        },
        "forgettingSpeed": [{ "triggerFlag": "newMonth", "decrease": 5 }],
        "affectionGrowthLimit": {
          "max": 1.5,
          "divisor": 9.0
        }
      },
      {
        "threshold": 300,
        "name": "爱慕",
        "describe": "视对方为自己所爱之人，会以不容拒绝的态度索求对方的亲密接触与情感回应，用看似任性的方式将对方留在自己身边。愿意为了得到对方而动用自己的资源、谋略与政治手腕。",
        "patienceUnit": "year",
        "visit": {
          "enabled": true,
          "probBase": 0.1,
          "probK": 0.001,
          "coolUnit": "day"
        },
        "forgettingSpeed": [{ "triggerFlag": "newYear", "decrease": 1 }],
        "affectionGrowthLimit": {
          "max": 20.0,
          "divisor": 2.0
        }
      },
      {
        "threshold": 9989,
        "name": "挚爱",
        "describe": "将对方视为自己绝对的挚爱，愿意终生与其相伴，对方的幸福便是自己存在的意义，将会永远铭记对方。",
        "patienceUnit": "year",
        "visit": {
          "enabled": true,
          "probBase": 0.2,
          "probK": 0.001,
          "coolUnit": "day"
        },
        "forgettingSpeed": [{ "triggerFlag": "newYear", "decrease": 0 }],
        "affectionGrowthLimit": {
          "max": 20.0,
          "divisor": 2.0
        }
      }
    ],
    "specials": [
      {
        "when": {
          "byFestival": ["MORIYA_SHRINE_GRAND_FESTIVAL"]
        },
        "action": {
          "do": "主持守矢神社大祭",
          "to": "守矢神社"
        },
        "priority": 90
      }
    ],
    "routine": [
      {
        "when": {
          "byNow": {
            "periodName": "清晨"
          }
        },
        "action": {
          "do": "吃早饭",
          "to": "$HOME"
        }
      },
      {
        "when": {
          "byNow": {
            "periodName": "上午"
          }
        },
        "action": {
          "do": "悠闲度过",
          "to": "$HOME"
        }
      },
      {
        "when": {
          "byNow": {
            "periodName": "中午"
          }
        },
        "action": {
          "do": "吃午饭",
          "to": "$HOME"
        }
      },
      {
        "when": {
          "byNow": {
            "periodName": "下午"
          }
        },
        "action": {
          "do": "悠闲度过",
          "to": "$HOME"
        }
      },
      {
        "when": {
          "byNow": {
            "periodName": "黄昏"
          }
        },
        "action": {
          "do": "吃晚饭",
          "to": "$HOME"
        }
      },
      {
        "when": {
          "byNow": {
            "periodName": "夜晚"
          }
        },
        "action": {
          "do": "休息",
          "to": "$HOME"
        }
      },
      {
        "when": {
          "byNow": {
            "periodName": "上半夜"
          }
        },
        "action": {
          "do": "睡觉",
          "to": "$HOME"
        }
      },
      {
        "when": {
          "byNow": {
            "periodName": "下半夜"
          }
        },
        "action": {
          "do": "睡觉",
          "to": "$HOME"
        }
      }
    ]
  }
}
